Metadata-Version: 1.1
Name: lfs-paypal
Version: 1.4.1
Summary: Integration of PayPal into LFS
Home-page: http://www.getlfs.com
Author: Kai Diefenbach
Author-email: kai.diefenbach@iqpp.de
License: BSD
Keywords: django e-commerce online-shop paypal
Platform: UNKNOWN
Classifier: Environment :: Web Environment
Classifier: Framework :: Django
Classifier: License :: OSI Approved :: BSD License
Classifier: Operating System :: OS Independent
Classifier: Programming Language :: Python
